AutoRequirements/AutoRequirements.py
AutoRequirements/__init__.py
tests/__init__.py
tests/conftest.py
tests/test_AutoRequirements.py
AutoReqs-0.1.3.dist-info/LICENSE
AutoReqs-0.1.3.dist-info/METADATA
AutoReqs-0.1.3.dist-info/WHEEL
AutoReqs-0.1.3.dist-info/entry_points.txt
AutoReqs-0.1.3.dist-info/top_level.txt
AutoReqs-0.1.3.dist-info/RECORD
